Metadata-Version: 1.1
Name: django-easy-poll
Version: 0.0.1
Summary: Django easy poll application
Home-page: https://github.com/hmtanbir/django-easy-poll
Author: Hasan Mohammad Tanbir
Author-email: tanbir2025@gmail.com
License: UNKNOWN
Download-URL: https://github.com/hmtanbir/django-easy-poll/archive/master.zip
Platform: UNKNOWN
Classifier: Development Status :: 4 - Beta
Classifier: Environment :: Web Environment
Classifier: Intended Audience :: Developers
Classifier: License :: OSI Approved :: MIT License
Classifier: Operating System :: OS Independent
Classifier: Programming Language :: Python
Classifier: Framework :: Django
